spdl/__init__.py
spdl/_internal/__init__.py
spdl/_internal/import_utils.py
spdl/dataloader/__init__.py
spdl/dataloader/_bg_task_executor.py
spdl/dataloader/_task_runner.py
spdl/dataloader/_utils.py
spdl/dataset/__init__.py
spdl/dataset/_dataset.py
spdl/dataset/_sql.py
spdl/dataset/_utils.py
spdl/dataset/imagenet.py
spdl/dataset/kinetics.py
spdl/dataset/librispeech.py
spdl/io/__init__.py
spdl/io/_async.py
spdl/io/_common.py
spdl/io/_concurrent.py
spdl/io/_config.py
spdl/io/_convert.py
spdl/io/_encoding.py
spdl/io/_misc.py
spdl/io/_preprocessing.py
spdl/io/_type_stub.py
spdl/lib/__init__.py
spdl/lib/_spdl_ffmpeg4.cpython-310-x86_64-linux-gnu.so
spdl/lib/_spdl_ffmpeg5.cpython-310-x86_64-linux-gnu.so
spdl/lib/_spdl_ffmpeg6.cpython-310-x86_64-linux-gnu.so
spdl/lib/_spdl_ffmpeg7.cpython-310-x86_64-linux-gnu.so
spdl/lib/libspdl_ffmpeg4.so
spdl/lib/libspdl_ffmpeg5.so
spdl/lib/libspdl_ffmpeg6.so
spdl/lib/libspdl_ffmpeg7.so
spdl/utils/__init__.py
spdl/utils/_build.py
spdl/utils/_ffmpeg.py
spdl/utils/_folly.py
spdl/utils/_futures.py
spdl/utils/_tracing.py
spdl_gpu-0.0.1.dist-info/LICENSE
spdl_gpu-0.0.1.dist-info/METADATA
spdl_gpu-0.0.1.dist-info/WHEEL
spdl_gpu-0.0.1.dist-info/top_level.txt
spdl_gpu-0.0.1.dist-info/RECORD
